odoo/addons/mgmtsystem_nonconformity_quality_control_oca/README.rst
odoo/addons/mgmtsystem_nonconformity_quality_control_oca/__init__.py
odoo/addons/mgmtsystem_nonconformity_quality_control_oca/__manifest__.py
odoo/addons/mgmtsystem_nonconformity_quality_control_oca/i18n/es.po
odoo/addons/mgmtsystem_nonconformity_quality_control_oca/i18n/it.po
odoo/addons/mgmtsystem_nonconformity_quality_control_oca/i18n/mgmtsystem_nonconformity_quality_control_oca.pot
odoo/addons/mgmtsystem_nonconformity_quality_control_oca/models/__init__.py
odoo/addons/mgmtsystem_nonconformity_quality_control_oca/models/mgmtsystem_nonconformity.py
odoo/addons/mgmtsystem_nonconformity_quality_control_oca/models/qc_inspection.py
odoo/addons/mgmtsystem_nonconformity_quality_control_oca/readme/CONTRIBUTORS.md
odoo/addons/mgmtsystem_nonconformity_quality_control_oca/readme/DESCRIPTION.md
odoo/addons/mgmtsystem_nonconformity_quality_control_oca/readme/USAGE.md
odoo/addons/mgmtsystem_nonconformity_quality_control_oca/static/description/icon.png
odoo/addons/mgmtsystem_nonconformity_quality_control_oca/static/description/index.html
odoo/addons/mgmtsystem_nonconformity_quality_control_oca/tests/__init__.py
odoo/addons/mgmtsystem_nonconformity_quality_control_oca/tests/test_inspection.py
odoo/addons/mgmtsystem_nonconformity_quality_control_oca/views/mgmtsystem_nonconformity.xml
odoo/addons/mgmtsystem_nonconformity_quality_control_oca/views/qc_inspection.xml
odoo_addon_mgmtsystem_nonconformity_quality_control_oca-17.0.1.0.0.4.dist-info/METADATA
odoo_addon_mgmtsystem_nonconformity_quality_control_oca-17.0.1.0.0.4.dist-info/WHEEL
odoo_addon_mgmtsystem_nonconformity_quality_control_oca-17.0.1.0.0.4.dist-info/top_level.txt
odoo_addon_mgmtsystem_nonconformity_quality_control_oca-17.0.1.0.0.4.dist-info/RECORD
