Metadata-Version: 2.1
Name: odoo-addon-mgmtsystem_nonconformity_quality_control_oca
Version: 17.0.1.0.0.4
Requires-Python: >=3.10
Requires-Dist: odoo-addon-mgmtsystem_nonconformity>=17.0dev,<17.1dev
Requires-Dist: odoo-addon-quality_control_oca>=17.0dev,<17.1dev
Requires-Dist: odoo>=17.0a,<17.1dev
Summary: Bridge module between Quality Control and Non Conformities
Home-page: https://github.com/OCA/management-system
License: AGPL-3
Author: Escodoo,Odoo Community Association (OCA)
Author-email: support@odoo-community.org
Classifier: Programming Language :: Python
Classifier: Framework :: Odoo
Classifier: Framework :: Odoo :: 17.0
Classifier: License :: OSI Approved :: GNU Affero General Public License v3
